catopalidi/__init__.py
catopalidi/image_generator.py
catopalidi/table_generator.py
catopalidi-0.1.dist-info/METADATA
catopalidi-0.1.dist-info/WHEEL
catopalidi-0.1.dist-info/top_level.txt
catopalidi-0.1.dist-info/RECORD
