Metadata-Version: 2.1
Name: catopalidi
Version: 0.1
Summary: Библиотека для генерации LaTeX кода для таблиц и изображений
Home-page: https://github.com/Enc0der/PythonCourse
Author: Aleksandra
Author-email: topalidia@gmail.com
Classifier: Programming Language :: Python :: 3
Classifier: License :: OSI Approved :: MIT License
Classifier: Operating System :: OS Independent
Requires-Python: >=3.6
